gapbot/__init__.py
gapbot/client/__init__.py
gapbot/client/gap.py
gapbot/client/methods/__init__.py
gapbot/client/methods/callbacks/__init__.py
gapbot/client/methods/callbacks/answer_callback.py
gapbot/client/methods/decorators/__init__.py
gapbot/client/methods/decorators/on_update.py
gapbot/client/methods/extra/__init__.py
gapbot/client/methods/extra/upload.py
gapbot/client/methods/game/__init__.py
gapbot/client/methods/game/get_game_config.py
gapbot/client/methods/game/get_game_data.py
gapbot/client/methods/game/get_top_players.py
gapbot/client/methods/game/set_game_data.py
gapbot/client/methods/game/set_game_event.py
gapbot/client/methods/messages/__init__.py
gapbot/client/methods/messages/delete_message.py
gapbot/client/methods/messages/edit_message.py
gapbot/client/methods/messages/send_action.py
gapbot/client/methods/messages/send_audio.py
gapbot/client/methods/messages/send_contact.py
gapbot/client/methods/messages/send_file.py
gapbot/client/methods/messages/send_image.py
gapbot/client/methods/messages/send_text.py
gapbot/client/methods/messages/send_video.py
gapbot/client/methods/messages/send_voice.py
gapbot/client/methods/payment/__init__.py
gapbot/client/methods/payment/get_invoice_status.py
gapbot/client/methods/payment/get_payment_status.py
gapbot/client/methods/payment/send_invoice.py
gapbot/client/methods/payment/verify_invoice.py
gapbot/client/methods/payment/verify_payment.py
gapbot/ext/__init__.py
gapbot/ext/base_client.py
GapBot-0.1.0.dist-info/LICENSE
GapBot-0.1.0.dist-info/METADATA
GapBot-0.1.0.dist-info/WHEEL
GapBot-0.1.0.dist-info/top_level.txt
GapBot-0.1.0.dist-info/RECORD
