Metadata-Version: 2.1
Name: GapBot
Version: 0.1.0
Summary: gapbot is python Gap messenger's api bot library
Home-page: https://github.com/MrMahdi313/gapbot
Author: MrMahdi313
Author-email: m.m.z.m12363@gmail.com
License: GNU Lesser General Public License v3.0
Project-URL: Tracker, https://github.com/MrMahdi313/gapbot/issues
Project-URL: API Docs Reference, https://developer.gap.im/doc
Project-URL: Source(Branch master), https://github.com/MrMahdi313/gapbot
Project-URL: Source(Branch dev), https://github.com/MrMahdi313/gapbot/tree/dev
Project-URL: Documentation, https://gapbot.readthedocs.io/en/latest
Keywords: gap bot api
Platform: UNKNOWN
Classifier: Programming Language :: Python :: 3
Classifier: Programming Language :: Python :: 3.6
Classifier: Intended Audience :: Developers
Classifier: Natural Language :: Persian
Classifier: Topic :: Internet
Classifier: Topic :: Software Development :: Libraries
Classifier: Topic :: Software Development :: Libraries :: Python Modules
Classifier: License :: OSI Approved :: GNU Lesser General Public License v3 (LGPLv3)
Requires-Python: >=3.6.0
Requires-Dist: Flask (==1.0.3)
Requires-Dist: requests (==2.22.0)
